setup.cfg
setup.py
parselmouth/__init__.py
parselmouth/base.py
parselmouth/config.py
parselmouth/constants.py
parselmouth/delivery.py
parselmouth/exceptions.py
parselmouth/model.py
parselmouth/targeting.py
parselmouth/tree_builder.py
parselmouth.egg-info/PKG-INFO
parselmouth.egg-info/SOURCES.txt
parselmouth.egg-info/dependency_links.txt
parselmouth.egg-info/pbr.json
parselmouth.egg-info/requires.txt
parselmouth.egg-info/top_level.txt
parselmouth/adapters/__init__.py
parselmouth/adapters/abstract_config.py
parselmouth/adapters/abstract_interface.py
parselmouth/adapters/dfp/__init__.py
parselmouth/adapters/dfp/client.py
parselmouth/adapters/dfp/config.py
parselmouth/adapters/dfp/constants.py
parselmouth/adapters/dfp/delivery_utils.py
parselmouth/adapters/dfp/interface.py
parselmouth/adapters/dfp/targeting_utils.py
parselmouth/adapters/dfp/utils.py
parselmouth/utils/__init__.py
parselmouth/utils/check.py
parselmouth/utils/dateutils.py
parselmouth/utils/enum.py
parselmouth/utils/timeout.py