Metadata-Version: 1.1
Name: parselmouth
Version: 1.1.1
Summary: An object oriented interface for ad provider services in python
Home-page: https://github.com/chartbeat-labs/parselmouth
Author: Paul Kiernan, Justin Mazur
Author-email: paulkiernan1@gmail.com, justindmazur@gmail.com
License: UNKNOWN
Download-URL: https://github.com/chartbeat-labs/parselmouth/tarball/1.1.1
Keywords: googleads,dfp,ad server,parselmouth,ad provider
Platform: UNKNOWN
